{
  "id": {
    "sheetNo": "1",
    "instructionInfo": {
      "heading": "Instructions",
      "description": "Read the below instructions carefully:",
      "instructions": [
        "Fill out all fields accurately.",
        "Students from outside JIIT must carry a valid ID card for entry."
      ],
      "checkboxStatus": {
        "show": true,
        "label": "I have read the instructions carefully.",
        "errorMsg": "Please check the box."
      }
    },
    "headerInfo": {
      "heading": "TALK:  BY PROF. H.C. VERMA"
    },
    "footerInfo": {
      "contactus": {
        "heading": "For any query please contact:",
        "person1": {
          "name": "Yash Mittal",
          "Phno": "+91 8570940287"
        },
        "person2": {
          "name": "Shantanu Pandey",
          "Phno": "+91 9026152678"
        }
      }
    },
    "formInfo": [
      {
        "heading": "Name",
        "name": "entry.name",
        "required": true,
        "type": "text",
        "placeholder": "Enter your name",
        "errorMsg": "Name is required."
      },
      {
        "heading": "Email",
        "name": "entry.email",
        "required": true,
        "type": "email",
        "placeholder": "Enter your email",
        "errorMsg": "Email is required.",
        "regex": "^[^\\s@]+@[^\\s@]+\\.[^\\s@]+$"
      },
      {
        "heading": "Phone",
        "name": "entry.phone",
        "required": true,
        "type": "text",
        "placeholder": "Enter your phone number",
        "errorMsg": "Phone number is required.",
        "regex": "^[0-9]{10}$"
      },
      {
        "heading": "College",
        "name": "entry.college",
        "required": true,
        "type": "radio",
        "labels": [
          "JIIT-62",
          "JIIT-128",
          "Others"
        ],
        "otherKey": ".other_option_response",
        "errorMsg": "Please select your college."
      },
      {
        "heading": "Enrollment No. (Only for Jaypee Institute of Information Technology Students)",
        "name": "entry.enroll",
        "required": false,
        "type": "text",
        "placeholder": "Enter your enrollment number",
        "errorMsg": "Enrollment number is required."
      },
      {
        "heading": "Branch (Only for Jaypee Institute of Information Technology Students)",
        "name": "entry.branch",
        "required": false,
        "type": "radio",
        "labels": [
          "Computer Science",
          "Information Technology",
          "Electronics & Communication",
          "EE VLSI",
          "ECE Adv Com.",
          "Mathematics & Computing",
          "BCA",
          "BBA",
          "MBA",
          "BioTech",
          "Others"
        ],
        "otherKey": ".other_option_response",
        "errorMsg": "Please select your branch."
      }
    ],
    "deadline": {
      "time": "2026-03-19T01:00"
    }
  },
  "xp30j03ozlrdihs1": {
    "sheetNo": 3,
    "instructionInfo": {
      "heading": "Instructions",
      "description": "Read the below instructions carefully:",
      "instructions": []
    },
    "headerInfo": {
      "heading": "testing"
    },
    "footerInfo": {
      "contactus": {
        "heading": "For any query please contact:",
        "person1": {
          "name": "",
          "Phno": ""
        },
        "person2": {
          "name": "",
          "Phno": ""
        }
      }
    },
    "formInfo": [
      {
        "heading": "name",
        "type": "text",
        "required": false,
        "name": "entry.name",
        "placeholder": "write your name",
        "errorMsg": "",
        "regex": "",
        "labels": [],
        "otherKey": "",
        "dropdownNames": [],
        "dropdownConfig": [],
        "allowedFileTypes": []
      }
    ],
    "deadline": {
      "time": "2025-04-17T16:31"
    }
  },
  "ryp9t52n9xrgnzug": {
    "sheetNo": 5,
    "instructionInfo": {
      "heading": "Instructions",
      "description": "Read the below instructions carefully:",
      "instructions": [
        "The mock interviews will be conducted on 3rd May, from 2:00 PM to 3:30 PM.",
        "You must upload your resume in a Google Drive link (ensure the link is open for all to view).",
        "If selected, you will receive a confirmation mail in the coming days."
      ]
    },
    "headerInfo": {
      "heading": "Mock Interview - CSE EVENT"
    },
    "footerInfo": {
      "contactus": {
        "heading": "For any query please contact:",
        "person1": {
          "name": "Aryan Goyal",
          "Phno": "9928590499"
        },
        "person2": {
          "name": "Yash Mittal",
          "Phno": "8570940287"
        }
      }
    },
    "formInfo": [
      {
        "heading": "Name",
        "type": "text",
        "required": true,
        "name": "entry.Name",
        "placeholder": "Enter your name",
        "errorMsg": "",
        "regex": "",
        "labels": [],
        "otherKey": "",
        "dropdownNames": [],
        "dropdownConfig": [],
        "allowedFileTypes": []
      },
      {
        "heading": "Enrollment_No.",
        "type": "text",
        "required": true,
        "name": "entry.Enrollment_No.",
        "placeholder": "Enter your Enrollment No",
        "errorMsg": "",
        "regex": "",
        "labels": [],
        "otherKey": "",
        "dropdownNames": [],
        "dropdownConfig": [],
        "allowedFileTypes": []
      },
      {
        "heading": "Current Year",
        "type": "radio",
        "required": true,
        "name": "entry.Current_Year",
        "placeholder": "Enter your current semester",
        "errorMsg": "",
        "regex": "",
        "labels": [
          "1st year",
          "2nd year",
          "3rd year",
          "4th year"
        ],
        "otherKey": "",
        "dropdownNames": [],
        "dropdownConfig": [],
        "allowedFileTypes": []
      },
      {
        "heading": "Branch",
        "type": "text",
        "required": true,
        "name": "entry.Branch",
        "placeholder": "Enter your branch",
        "errorMsg": "",
        "regex": "",
        "labels": [],
        "otherKey": "",
        "dropdownNames": [],
        "dropdownConfig": [],
        "allowedFileTypes": []
      },
      {
        "heading": "Current CGPA",
        "type": "text",
        "required": true,
        "name": "entry.Current_CGPA",
        "placeholder": "Enter your current cgpa",
        "errorMsg": "",
        "regex": "",
        "labels": [],
        "otherKey": "",
        "dropdownNames": [],
        "dropdownConfig": [],
        "allowedFileTypes": []
      },
      {
        "heading": "Portfolio Link (if any)",
        "type": "text",
        "required": false,
        "name": "entry.Portfolio_Link_(if_any)",
        "placeholder": "Enter your portfolio link",
        "errorMsg": "",
        "regex": "",
        "labels": [],
        "otherKey": "",
        "dropdownNames": [],
        "dropdownConfig": [],
        "allowedFileTypes": []
      },
      {
        "heading": "Github Link",
        "type": "text",
        "required": true,
        "name": "entry.Github_Link",
        "placeholder": "Enter your github link",
        "errorMsg": "",
        "regex": "",
        "labels": [],
        "otherKey": "",
        "dropdownNames": [],
        "dropdownConfig": [],
        "allowedFileTypes": []
      },
      {
        "heading": "Linkedin url",
        "type": "text",
        "required": true,
        "name": "entry.Linkedin_url",
        "placeholder": "Enter your Linkedin url",
        "errorMsg": "",
        "regex": "",
        "labels": [],
        "otherKey": "",
        "dropdownNames": [],
        "dropdownConfig": [],
        "allowedFileTypes": []
      },
      {
        "heading": "Resume Drive Link",
        "type": "text",
        "required": true,
        "name": "entry.Resume_Drive_Link",
        "placeholder": "Enter your Resume Link",
        "errorMsg": "",
        "regex": "",
        "labels": [],
        "otherKey": "",
        "dropdownNames": [],
        "dropdownConfig": [],
        "allowedFileTypes": []
      }
    ],
    "deadline": {
      "time": "2025-05-04T12:00"
    }
  },
  "ho6msjapuz7y873h": {
    "sheetNo": 6,
    "instructionInfo": {
      "heading": "Instructions",
      "description": "Read the below instructions carefully:",
      "instructions": [
        "The event has two rounds: POINTLESS, where participants give the most correct yet rare answer, and Reverse Prompt Engineering, where participants replicate images using prompts on Gemini.",
        "The team leader must give correct email ID for signing in; ID and password for the event platform will be sent to this email one day before the event and must not be shared.",
        "The event will be held at location CL01 on 4th May 2025 from 3:00 PM to 4:30 PM."
      ]
    },
    "headerInfo": {
      "heading": "Pointless - CSE EVENT"
    },
    "footerInfo": {
      "contactus": {
        "heading": "For any query please contact:",
        "person1": {
          "name": "Aryan Goyal",
          "Phno": "9928590499"
        },
        "person2": {
          "name": "Arnav Khandelwal",
          "Phno": "7042273876"
        }
      }
    },
    "formInfo": [
      {
        "heading": "Team Name",
        "type": "text",
        "required": true,
        "name": "entry.Team_Name",
        "placeholder": "Enter your team name",
        "errorMsg": "",
        "regex": "",
        "labels": [],
        "otherKey": "",
        "dropdownNames": [],
        "dropdownConfig": [],
        "allowedFileTypes": []
      },
      {
        "heading": "Leader Name",
        "type": "text",
        "required": true,
        "name": "entry.Leader_Name",
        "placeholder": "Enter your leader name",
        "errorMsg": "",
        "regex": "",
        "labels": [],
        "otherKey": "",
        "dropdownNames": [],
        "dropdownConfig": [],
        "allowedFileTypes": []
      },
      {
        "heading": "Enrollment No.",
        "type": "text",
        "required": true,
        "name": "entry.Enrollment_No.",
        "placeholder": "Enter your Enrollment Number",
        "errorMsg": "",
        "regex": "",
        "labels": [],
        "otherKey": "",
        "dropdownNames": [],
        "dropdownConfig": [],
        "allowedFileTypes": []
      },
      {
        "heading": "Current Year",
        "type": "radio",
        "required": true,
        "name": "entry.Current_Year",
        "placeholder": "Enter your Current Semester ",
        "errorMsg": "",
        "regex": "",
        "labels": [
          "1st year",
          "2nd year",
          "3rd year",
          "4th year"
        ],
        "otherKey": "",
        "dropdownNames": [],
        "dropdownConfig": [],
        "allowedFileTypes": []
      },
      {
        "heading": "Branch",
        "type": "text",
        "required": true,
        "name": "entry.Branch",
        "placeholder": "Enter your branch ",
        "errorMsg": "",
        "regex": "",
        "labels": [],
        "otherKey": "",
        "dropdownNames": [],
        "dropdownConfig": [],
        "allowedFileTypes": []
      },
      {
        "heading": "Leader Email Id ( Used for signing in )",
        "type": "text",
        "required": true,
        "name": "entry.Leader_Email_Id_(_Used_for_signing_in_)",
        "placeholder": "Enter your Email id",
        "errorMsg": "",
        "regex": "",
        "labels": [],
        "otherKey": "",
        "dropdownNames": [],
        "dropdownConfig": [],
        "allowedFileTypes": []
      },
      {
        "heading": "Member 1 Name",
        "type": "text",
        "required": false,
        "name": "entry.Member_1_Name",
        "placeholder": "Enter your Name",
        "errorMsg": "",
        "regex": "",
        "labels": [],
        "otherKey": "",
        "dropdownNames": [],
        "dropdownConfig": [],
        "allowedFileTypes": []
      },
      {
        "heading": "Member 1 Enrollment No",
        "type": "text",
        "required": false,
        "name": "entry.Member_1_Enrollment_No",
        "placeholder": "Enter your enrollment number",
        "errorMsg": "",
        "regex": "",
        "labels": [],
        "otherKey": "",
        "dropdownNames": [],
        "dropdownConfig": [],
        "allowedFileTypes": []
      },
      {
        "heading": "Current Year",
        "type": "radio",
        "required": false,
        "name": "entry.Current_Year",
        "placeholder": "",
        "errorMsg": "",
        "regex": "",
        "labels": [
          "1st year",
          "2nd year",
          "3rd year",
          "4th year"
        ],
        "otherKey": "",
        "dropdownNames": [],
        "dropdownConfig": [],
        "allowedFileTypes": []
      },
      {
        "heading": "Branch",
        "type": "text",
        "required": false,
        "name": "entry.Branch",
        "placeholder": "Enter your Branch",
        "errorMsg": "",
        "regex": "",
        "labels": [],
        "otherKey": "",
        "dropdownNames": [],
        "dropdownConfig": [],
        "allowedFileTypes": []
      },
      {
        "heading": "Member 2 Name",
        "type": "text",
        "required": false,
        "name": "entry.Member_2_Name",
        "placeholder": "Enter your Name",
        "errorMsg": "",
        "regex": "",
        "labels": [],
        "otherKey": "",
        "dropdownNames": [],
        "dropdownConfig": [],
        "allowedFileTypes": []
      },
      {
        "heading": "Member 2 Enrollment No",
        "type": "text",
        "required": false,
        "name": "entry.Member_2_Enrollment_No",
        "placeholder": "Enter your enrollment number",
        "errorMsg": "",
        "regex": "",
        "labels": [],
        "otherKey": "",
        "dropdownNames": [],
        "dropdownConfig": [],
        "allowedFileTypes": []
      },
      {
        "heading": "Branch",
        "type": "text",
        "required": false,
        "name": "entry.Branch",
        "placeholder": "Enter your Branch",
        "errorMsg": "",
        "regex": "",
        "labels": [],
        "otherKey": "",
        "dropdownNames": [],
        "dropdownConfig": [],
        "allowedFileTypes": []
      },
      {
        "heading": "Current Year",
        "type": "radio",
        "required": false,
        "name": "entry.Current_Year",
        "placeholder": "",
        "errorMsg": "",
        "regex": "",
        "labels": [
          "1st year",
          "2nd year",
          "3rd year",
          "4th year"
        ],
        "otherKey": "",
        "dropdownNames": [],
        "dropdownConfig": [],
        "allowedFileTypes": []
      }
    ],
    "deadline": {
      "time": "2025-05-04T12:00"
    }
  },
  "uxdxwe2jfs0l58xi": {
    "sheetNo": 7,
    "instructionInfo": {
      "heading": "Instructions",
      "description": "Read the below instructions carefully:",
      "instructions": [
        "Teams of 3 are compulsory.",
        "Level 1: Solve 20 Bollywood-style ECE riddles; faster answers get higher points.",
        "Level 2: Solve a breadboard circuit with one member handling hardware; fallback by decoding a Hindi song if needed.",
        "Level 3: Complete a relay circuit race with 1 minute per teammate and no talking."
      ]
    },
    "headerInfo": {
      "heading": "AstroVolt - Ece Event"
    },
    "footerInfo": {
      "contactus": {
        "heading": "For any query please contact:",
        "person1": {
          "name": "Shantanu Pandey",
          "Phno": "90261 52678"
        },
        "person2": {
          "name": "Manya Dubey",
          "Phno": "72918 44164"
        }
      }
    },
    "formInfo": [
      {
        "heading": "Team Name",
        "type": "text",
        "required": true,
        "name": "entry.Team_Name",
        "placeholder": "Enter your team name",
        "errorMsg": "",
        "regex": "",
        "labels": [],
        "otherKey": "",
        "dropdownNames": [],
        "dropdownConfig": [],
        "allowedFileTypes": []
      },
      {
        "heading": "Member 1 Name",
        "type": "text",
        "required": true,
        "name": "entry.Member_1_Name",
        "placeholder": "Enter your name",
        "errorMsg": "",
        "regex": "",
        "labels": [],
        "otherKey": "",
        "dropdownNames": [],
        "dropdownConfig": [],
        "allowedFileTypes": []
      },
      {
        "heading": "Member 1 Email",
        "type": "email",
        "required": true,
        "name": "entry.Member_1_Email",
        "placeholder": "Enter your email",
        "errorMsg": "",
        "regex": "",
        "labels": [],
        "otherKey": "",
        "dropdownNames": [],
        "dropdownConfig": [],
        "allowedFileTypes": []
      },
      {
        "heading": "Member 1 Enrollment No.",
        "type": "text",
        "required": true,
        "name": "entry.Member_1_Enrollment_No.",
        "placeholder": "Enter your enrollment number",
        "errorMsg": "",
        "regex": "",
        "labels": [],
        "otherKey": "",
        "dropdownNames": [],
        "dropdownConfig": [],
        "allowedFileTypes": []
      },
      {
        "heading": "Member 1 Branch",
        "type": "text",
        "required": true,
        "name": "entry.Member_1_Branch",
        "placeholder": "Enter your branch",
        "errorMsg": "",
        "regex": "",
        "labels": [],
        "otherKey": "",
        "dropdownNames": [],
        "dropdownConfig": [],
        "allowedFileTypes": []
      },
      {
        "heading": "Current Year",
        "type": "radio",
        "required": true,
        "name": "entry.Current_Year",
        "placeholder": "",
        "errorMsg": "",
        "regex": "",
        "labels": [
          "1st year",
          "2nd year",
          "3rd year",
          "4th year"
        ],
        "otherKey": "",
        "dropdownNames": [],
        "dropdownConfig": [],
        "allowedFileTypes": []
      },
      {
        "heading": "Member 2 Name",
        "type": "text",
        "required": true,
        "name": "entry.Member_2_Name",
        "placeholder": "Enter your name",
        "errorMsg": "",
        "regex": "",
        "labels": [],
        "otherKey": "",
        "dropdownNames": [],
        "dropdownConfig": [],
        "allowedFileTypes": []
      },
      {
        "heading": "Member 2 Email",
        "type": "email",
        "required": true,
        "name": "entry.Member_2_Email",
        "placeholder": "Enter your Email",
        "errorMsg": "",
        "regex": "",
        "labels": [],
        "otherKey": "",
        "dropdownNames": [],
        "dropdownConfig": [],
        "allowedFileTypes": []
      },
      {
        "heading": "Member 2 Enrollment No.",
        "type": "text",
        "required": true,
        "name": "entry.Member_2_Enrollment_No.",
        "placeholder": "Enter your enrollment number",
        "errorMsg": "",
        "regex": "",
        "labels": [],
        "otherKey": "",
        "dropdownNames": [],
        "dropdownConfig": [],
        "allowedFileTypes": []
      },
      {
        "heading": "Member 2 Branch",
        "type": "text",
        "required": true,
        "name": "entry.Member_2_Branch",
        "placeholder": "Enter your branch",
        "errorMsg": "",
        "regex": "",
        "labels": [],
        "otherKey": "",
        "dropdownNames": [],
        "dropdownConfig": [],
        "allowedFileTypes": []
      },
      {
        "heading": "Current Year",
        "type": "radio",
        "required": true,
        "name": "entry.Current_Year",
        "placeholder": "",
        "errorMsg": "",
        "regex": "",
        "labels": [
          "1st year",
          "2nd year",
          "3rd year",
          "4th year"
        ],
        "otherKey": "",
        "dropdownNames": [],
        "dropdownConfig": [],
        "allowedFileTypes": []
      },
      {
        "heading": "Member 3 Name",
        "type": "text",
        "required": true,
        "name": "entry.Member_3_Name",
        "placeholder": "Enter your name",
        "errorMsg": "",
        "regex": "",
        "labels": [],
        "otherKey": "",
        "dropdownNames": [],
        "dropdownConfig": [],
        "allowedFileTypes": []
      },
      {
        "heading": "Member 3 Email",
        "type": "text",
        "required": true,
        "name": "entry.Member_3_Email",
        "placeholder": "Enter your Email",
        "errorMsg": "",
        "regex": "",
        "labels": [],
        "otherKey": "",
        "dropdownNames": [],
        "dropdownConfig": [],
        "allowedFileTypes": []
      },
      {
        "heading": "Member 3 Enrollment No.",
        "type": "text",
        "required": true,
        "name": "entry.Member_3_Enrollment_No.",
        "placeholder": "Enter your enrollment number",
        "errorMsg": "",
        "regex": "",
        "labels": [],
        "otherKey": "",
        "dropdownNames": [],
        "dropdownConfig": [],
        "allowedFileTypes": []
      },
      {
        "heading": "Member 3 Branch",
        "type": "text",
        "required": true,
        "name": "entry.Member_3_Branch",
        "placeholder": "Enter your branch",
        "errorMsg": "",
        "regex": "",
        "labels": [],
        "otherKey": "",
        "dropdownNames": [],
        "dropdownConfig": [],
        "allowedFileTypes": []
      },
      {
        "heading": "Currrent year",
        "type": "radio",
        "required": true,
        "name": "entry.Currrent_year",
        "placeholder": "",
        "errorMsg": "",
        "regex": "",
        "labels": [
          "1st year",
          "2nd year",
          "3rd year",
          "4th year"
        ],
        "otherKey": "",
        "dropdownNames": [],
        "dropdownConfig": [],
        "allowedFileTypes": []
      }
    ],
    "deadline": {
      "time": "2025-05-04T12:00"
    }
  },
  "cpqk29jus9m4zlzh": {
    "sheetNo": 8,
    "instructionInfo": {
      "heading": "Instructions",
      "description": "Read the below instructions carefully:",
      "instructions": [
        "Each performance must be based on 90 seconds. Performers must arrange their own instruments if required.",
        "Before performing, each participant must submit a self-score. If it matches the judges’ average score after the performance, the participant wins.",
        "A cash prize of ₹7,000 will be awarded immediately (hand-to-hand).",
        "In case of multiple winners, a tie-breaker will be held. Judges may also decide to split the prize at their discretion.",
        "Participants must answer all form questions thoughtfully.",
        "You already know the drill of this event so prepare accordingly. Best of Luck😎😏"
      ]
    },
    "headerInfo": {
      "heading": "OPTICA GOT TALENT"
    },
    "footerInfo": {
      "contactus": {
        "heading": "For any query please contact:",
        "person1": {
          "name": "Shantanu",
          "Phno": "9026152678"
        },
        "person2": {
          "name": "Sai",
          "Phno": "7439557090"
        }
      }
    },
    "formInfo": [
      {
        "heading": "Name",
        "type": "text",
        "required": true,
        "name": "entry.Name",
        "placeholder": "Enter your name",
        "errorMsg": "",
        "regex": "",
        "labels": [],
        "otherKey": "",
        "dropdownNames": [],
        "dropdownConfig": [],
        "allowedFileTypes": []
      },
      {
        "heading": "Email",
        "type": "email",
        "required": true,
        "name": "entry.Email",
        "placeholder": "Enter your email",
        "errorMsg": "",
        "regex": "",
        "labels": [],
        "otherKey": "",
        "dropdownNames": [],
        "dropdownConfig": [],
        "allowedFileTypes": []
      },
      {
        "heading": "Phone",
        "type": "text",
        "required": true,
        "name": "entry.Phone",
        "placeholder": "Enter your phone no.",
        "errorMsg": "",
        "regex": "^[0-9]{10}$",
        "labels": [],
        "otherKey": "",
        "dropdownNames": [],
        "dropdownConfig": [],
        "allowedFileTypes": []
      },
      {
        "heading": "Branch",
        "type": "text",
        "required": true,
        "name": "entry.Branch",
        "placeholder": "Enter your branch",
        "errorMsg": "",
        "regex": "",
        "labels": [],
        "otherKey": "",
        "dropdownNames": [],
        "dropdownConfig": [],
        "allowedFileTypes": []
      },
      {
        "heading": "Do you have any sibling ?",
        "type": "radio",
        "required": true,
        "name": "entry.Do_you_have_any_sibling_?",
        "placeholder": "",
        "errorMsg": "",
        "regex": "",
        "labels": [
          "Yes",
          "No"
        ],
        "otherKey": "",
        "dropdownNames": [],
        "dropdownConfig": [],
        "allowedFileTypes": []
      },
      {
        "heading": "Describe yourself in three words",
        "type": "textarea",
        "required": true,
        "name": "entry.Describe_yourself_in_three_words",
        "placeholder": "",
        "errorMsg": "",
        "regex": "",
        "labels": [],
        "otherKey": "",
        "dropdownNames": [],
        "dropdownConfig": [],
        "allowedFileTypes": []
      },
      {
        "heading": "What is your relationship status?",
        "type": "radio",
        "required": true,
        "name": "entry.What_is_your_relationship_status?",
        "placeholder": "",
        "errorMsg": "",
        "regex": "",
        "labels": [
          "Yes",
          "No"
        ],
        "otherKey": "",
        "dropdownNames": [],
        "dropdownConfig": [],
        "allowedFileTypes": []
      },
      {
        "heading": "What is one daring thing you have done in your life so far?",
        "type": "textarea",
        "required": true,
        "name": "entry.What_is_one_daring_thing_you_have_done_in_your_life_so_far?",
        "placeholder": "",
        "errorMsg": "",
        "regex": "",
        "labels": [],
        "otherKey": "",
        "dropdownNames": [],
        "dropdownConfig": [],
        "allowedFileTypes": []
      },
      {
        "heading": "What is your biggest achievement in life so far?",
        "type": "textarea",
        "required": true,
        "name": "entry.What_is_your_biggest_achievement_in_life_so_far?",
        "placeholder": "",
        "errorMsg": "",
        "regex": "",
        "labels": [],
        "otherKey": "",
        "dropdownNames": [],
        "dropdownConfig": [],
        "allowedFileTypes": []
      },
      {
        "heading": "What is your life goal?",
        "type": "textarea",
        "required": true,
        "name": "entry.What_is_your_life_goal?",
        "placeholder": "",
        "errorMsg": "",
        "regex": "",
        "labels": [],
        "otherKey": "",
        "dropdownNames": [],
        "dropdownConfig": [],
        "allowedFileTypes": []
      },
      {
        "heading": "If you had to roast yourself in one line, what would you say?",
        "type": "textarea",
        "required": true,
        "name": "entry.If_you_had_to_roast_yourself_in_one_line,_what_would_you_say?",
        "placeholder": "",
        "errorMsg": "",
        "regex": "",
        "labels": [],
        "otherKey": "",
        "dropdownNames": [],
        "dropdownConfig": [],
        "allowedFileTypes": []
      },
      {
        "heading": "If you were a bad habit, what would you be?",
        "type": "textarea",
        "required": true,
        "name": "entry.If_you_were_a_bad_habit,_what_would_you_be?",
        "placeholder": "",
        "errorMsg": "",
        "regex": "",
        "labels": [],
        "otherKey": "",
        "dropdownNames": [],
        "dropdownConfig": [],
        "allowedFileTypes": []
      },
      {
        "heading": "Whats the most shameless thing youve done for attention?",
        "type": "textarea",
        "required": true,
        "name": "entry.Whats_the_most_shameless_thing_youve_done_for_attention?",
        "placeholder": "",
        "errorMsg": "",
        "regex": "",
        "labels": [],
        "otherKey": "",
        "dropdownNames": [],
        "dropdownConfig": [],
        "allowedFileTypes": []
      },
      {
        "heading": "Describe your talent performance using only dirty talk (keep it college-appropriate 😉).",
        "type": "textarea",
        "required": true,
        "name": "entry.Describe_your_talent_performance_using_only_dirty_talk_(keep_it_college-appropriate_😉).",
        "placeholder": "",
        "errorMsg": "",
        "regex": "",
        "labels": [],
        "otherKey": "",
        "dropdownNames": [],
        "dropdownConfig": [],
        "allowedFileTypes": []
      }
    ],
    "deadline": {
      "time": "2025-05-05T12:00"
    }
  },
  "nqc3wxktsyz7a96x": {
    "sheetNo": 9,
    "instructionInfo": {
      "heading": "Instructions",
      "description": "Read the below instructions carefully:",
      "instructions": [
        "All participants must be present before the competition starts. 4th May,2025 ,OAT , 10:00 AM",
        "Participants must maintain discipline and follow all instructions given by the volunteers or organizing team during the event.",
        "QR codes must not be destroyed",
        "Each participant must bring their own mobile phone for the first round.",
        "Participants must stay within the given locations.  (Specifically, you are allowed only on the Ground Floor of AAB1 (Academic Building 1). Do not go upstairs.)"
      ]
    },
    "headerInfo": {
      "heading": "Optisus X Stars Wars"
    },
    "footerInfo": {
      "contactus": {
        "heading": "For any query please contact:",
        "person1": {
          "name": "Aryan Goyal",
          "Phno": "9928590499"
        },
        "person2": {
          "name": "Bhavishy",
          "Phno": "9610363350"
        }
      }
    },
    "formInfo": [
      {
        "heading": "Team Name",
        "type": "text",
        "required": true,
        "name": "entry.Team_Name",
        "placeholder": "Enter your team name",
        "errorMsg": "",
        "regex": "",
        "labels": [],
        "otherKey": "",
        "dropdownNames": [],
        "dropdownConfig": [],
        "allowedFileTypes": []
      },
      {
        "heading": "Team Leader Name",
        "type": "text",
        "required": true,
        "name": "entry.Team_Leader_Name",
        "placeholder": "Enter your name",
        "errorMsg": "",
        "regex": "",
        "labels": [],
        "otherKey": "",
        "dropdownNames": [],
        "dropdownConfig": [],
        "allowedFileTypes": []
      },
      {
        "heading": "Leader Enrollment No.",
        "type": "text",
        "required": true,
        "name": "entry.Leader_Enrollment_No.",
        "placeholder": "Enter your enrollment no.",
        "errorMsg": "",
        "regex": "",
        "labels": [],
        "otherKey": "",
        "dropdownNames": [],
        "dropdownConfig": [],
        "allowedFileTypes": []
      },
      {
        "heading": "Leader Email",
        "type": "email",
        "required": true,
        "name": "entry.Leader_Email",
        "placeholder": "Enter your email",
        "errorMsg": "",
        "regex": "",
        "labels": [],
        "otherKey": "",
        "dropdownNames": [],
        "dropdownConfig": [],
        "allowedFileTypes": []
      },
      {
        "heading": "Phone No",
        "type": "text",
        "required": true,
        "name": "entry.Phone_No",
        "placeholder": "Enter your Phone no",
        "errorMsg": "",
        "regex": "",
        "labels": [],
        "otherKey": "",
        "dropdownNames": [],
        "dropdownConfig": [],
        "allowedFileTypes": []
      },
      {
        "heading": "Member 1 Name",
        "type": "text",
        "required": true,
        "name": "entry.Member_1_Name",
        "placeholder": "Enter your name",
        "errorMsg": "",
        "regex": "",
        "labels": [],
        "otherKey": "",
        "dropdownNames": [],
        "dropdownConfig": [],
        "allowedFileTypes": []
      },
      {
        "heading": "Member 2 Name",
        "type": "text",
        "required": true,
        "name": "entry.Member_2_Name",
        "placeholder": "Enter your name",
        "errorMsg": "",
        "regex": "",
        "labels": [],
        "otherKey": "",
        "dropdownNames": [],
        "dropdownConfig": [],
        "allowedFileTypes": []
      },
      {
        "heading": "Member 3 Nmae",
        "type": "text",
        "required": true,
        "name": "entry.Member_3_Nmae",
        "placeholder": "Enter your name",
        "errorMsg": "",
        "regex": "",
        "labels": [],
        "otherKey": "",
        "dropdownNames": [],
        "dropdownConfig": [],
        "allowedFileTypes": []
      },
      {
        "heading": "Which side you are ?",
        "type": "radio",
        "required": true,
        "name": "entry.Which_side_you_are_?",
        "placeholder": "",
        "errorMsg": "",
        "regex": "",
        "labels": [
          "Sith (dark side)  ",
          " Jedi (light side)"
        ],
        "otherKey": "",
        "dropdownNames": [],
        "dropdownConfig": [],
        "allowedFileTypes": []
      }
    ],
    "deadline": {
      "time": "2025-05-05T12:00"
    }
  }
}
